kamui/__init__.py
kamui/core.py
kamui/utils.py
kamui-0.1.2.dist-info/LICENSE
kamui-0.1.2.dist-info/METADATA
kamui-0.1.2.dist-info/WHEEL
kamui-0.1.2.dist-info/top_level.txt
kamui-0.1.2.dist-info/RECORD
