Metadata-Version: 2.1
Name: kamui
Version: 0.1.2
Summary: A Python package for phase unwrapping
Home-page: https://github.com/yoyololicon/kamui
Author: Chin-Yun Yu
Author-email: chin-yun.yu@qmul.ac.uk
Classifier: Programming Language :: Python :: 3
Classifier: License :: OSI Approved :: MIT License
Classifier: Operating System :: OS Independent
Requires-Python: >=3.6
License-File: LICENSE
Requires-Dist: numpy
Requires-Dist: scipy
Provides-Extra: extra
Requires-Dist: PyMaxflow; extra == "extra"
